LICENSE
MANIFEST.in
README.rst
setup.cfg
setup.py
django_table_sharding/__init__.py
django_table_sharding/apps.py
django_table_sharding/managers.py
django_table_sharding/tests.py
django_table_sharding/utils.py
django_table_sharding.egg-info/PKG-INFO
django_table_sharding.egg-info/SOURCES.txt
django_table_sharding.egg-info/dependency_links.txt
django_table_sharding.egg-info/not-zip-safe
django_table_sharding.egg-info/top_level.txt
django_table_sharding/management/.DS_Store
django_table_sharding/management/__init__.py
django_table_sharding/management/__pycache__/__init__.cpython-37.pyc
django_table_sharding/management/commands/__init__.py
django_table_sharding/management/commands/migrate.py
django_table_sharding/management/commands/__pycache__/__init__.cpython-37.pyc
django_table_sharding/management/commands/__pycache__/migrate.cpython-37.pyc