Metadata-Version: 1.1
Name: django-table-sharding
Version: 1.0.2
Summary: A Django app to automatically handle sharding model tables in MySQL.
Home-page: https://github.com/rayhern/django-table-sharding
Author: Raymond Hernandez
Author-email: bizong@gmail.com
License: BSD
Platform: UNKNOWN
Classifier: Environment :: Web Environment
Classifier: Framework :: Django
Classifier: Framework :: Django :: 2.2
Classifier: Intended Audience :: Developers
Classifier: License :: OSI Approved :: BSD License
Classifier: Operating System :: OS Independent
Classifier: Programming Language :: Python
Classifier: Programming Language :: Python :: 3
Classifier: Programming Language :: Python :: 3.6
Classifier: Programming Language :: Python :: 3.7
Classifier: Programming Language :: Python :: 3.8
